finbourne_horizon/__init__.py
finbourne_horizon/api/__init__.py
finbourne_horizon/api/instrument_api.py
finbourne_horizon/api/integrations_api.py
finbourne_horizon/api/logs_api.py
finbourne_horizon/api/process_history_api.py
finbourne_horizon/api/runs_api.py
finbourne_horizon/api/vendor_api.py
finbourne_horizon/api_client.py
finbourne_horizon/api_response.py
finbourne_horizon/configuration.py
finbourne_horizon/exceptions.py
finbourne_horizon/extensions/__init__.py
finbourne_horizon/extensions/api_client.py
finbourne_horizon/extensions/api_client_factory.py
finbourne_horizon/extensions/api_configuration.py
finbourne_horizon/extensions/configuration_loaders.py
finbourne_horizon/extensions/configuration_options.py
finbourne_horizon/extensions/file_access_token.py
finbourne_horizon/extensions/proxy_config.py
finbourne_horizon/extensions/refreshing_token.py
finbourne_horizon/extensions/rest.py
finbourne_horizon/extensions/retry.py
finbourne_horizon/extensions/socket_keep_alive.py
finbourne_horizon/extensions/tcp_keep_alive_connector.py
finbourne_horizon/models/__init__.py
finbourne_horizon/models/allowed_parameter_value.py
finbourne_horizon/models/audit_complete_request.py
finbourne_horizon/models/audit_complete_response.py
finbourne_horizon/models/audit_file_details.py
finbourne_horizon/models/audit_update_request.py
finbourne_horizon/models/audit_update_response.py
finbourne_horizon/models/cancel_run_request.py
finbourne_horizon/models/create_instance_request.py
finbourne_horizon/models/enrichment_response.py
finbourne_horizon/models/execute_instance_response.py
finbourne_horizon/models/external_log_insertion_request.py
finbourne_horizon/models/external_log_record.py
finbourne_horizon/models/field_mapping.py
finbourne_horizon/models/file_details.py
finbourne_horizon/models/i_field_mapping.py
finbourne_horizon/models/i_integration_log_response.py
finbourne_horizon/models/i_property_mapping.py
finbourne_horizon/models/identifiers.py
finbourne_horizon_sdk-2.3.2.dist-info/METADATA
finbourne_horizon_sdk-2.3.2.dist-info/WHEEL
finbourne_horizon_sdk-2.3.2.dist-info/RECORD
